{
  "alunos": [
    {
      "id": 7,
      "name": "Bruna"
    },
    {
      "id": 8,
      "name": "Luan"
    },
    {
      "id": 10,
      "name": "José"
    },
    {
      "name": "jeniffer",
      "id": 11
    },
    {
      "name": "Victor",
      "id": 13
    },
    {
      "name": "Cleber",
      "id": 14
    },
    {
      "name": "Samira",
      "id": 15
    },
    {
      "name": "Mariah",
      "id": 16
    },
    {
      "name": "Leticia",
      "id": 17
    },
    {
      "name": "Luiz",
      "id": 18
    }
  ]
}